{
  "name": "ShoppingCartItem",
  "base": "PersistedModel",
  "idInjection": true,
  "strict": true,
  "options": {
    "validateUpsert": true
  },
  "properties": {
    "id": false,
    "productId": {
      "type": "string",
      "required": true
    },
    "addDate": {
      "type": "string",
      "required": false
    },
    "quantity": {
      "type": "number",
      "required": true
    },
    "price": {
      "type": "number",
      "required": true
    }
  },
  "validations": [],
  "relations": {},
  "acls": [],
  "methods": {},
  "mixins": {}
}